{
    "Ar36": {
        "error": 0.0006356086837027688,
        "error_type": "SEM",
        "filter_outliers_dict": {
            "filter_outliers": true,
            "iterations": 1,
            "std_devs": 3,
            "use_iqr_filtering": false,
            "use_standard_deviation_filtering": false
        },
        "fit": "linear",
        "fn": 340,
        "include_baseline_error": true,
        "n": 340,
        "outlier_excluded": [],
        "reviewed": true,
        "user_excluded": [],
        "value": 0.16976373659028196
    },
    "Ar37": {
        "error": 0.015044350385534538,
        "error_type": "SEM",
        "filter_outliers_dict": {
            "filter_outliers": true,
            "iterations": 1,
            "std_devs": 3,
            "use_iqr_filtering": false,
            "use_standard_deviation_filtering": false
        },
        "fit": "linear",
        "fn": 340,
        "include_baseline_error": true,
        "n": 340,
        "outlier_excluded": [],
        "reviewed": true,
        "user_excluded": [],
        "value": 1.6156675352895646
    },
    "Ar38": {
        "error": 0.005743515503445683,
        "error_type": "SEM",
        "filter_outliers_dict": {
            "filter_outliers": true,
            "iterations": 1,
            "std_devs": 3,
            "use_iqr_filtering": false,
            "use_standard_deviation_filtering": false
        },
        "fit": "linear",
        "fn": 338,
        "include_baseline_error": true,
        "n": 340,
        "outlier_excluded": [
            276,
            302
        ],
        "reviewed": true,
        "user_excluded": [],
        "value": 0.23575034738331568
    },
    "Ar39": {
        "error": 0.00796541057209869,
        "error_type": "SEM",
        "filter_outliers_dict": {
            "filter_outliers": true,
            "iterations": 1,
            "std_devs": 3,
            "use_iqr_filtering": false,
            "use_standard_deviation_filtering": false
        },
        "fit": "linear",
        "fn": 339,
        "include_baseline_error": true,
        "n": 340,
        "outlier_excluded": [
            12
        ],
        "reviewed": true,
        "user_excluded": [],
        "value": 3.4759296424370576
    },
    "Ar40": {
        "error": 0.030706183061651564,
        "error_type": "SEM",
        "filter_outliers_dict": {
            "filter_outliers": false,
            "iterations": 1,
            "std_devs": 3,
            "use_iqr_filtering": false,
            "use_standard_deviation_filtering": false
        },
        "fit": "parabolic",
        "fn": 340,
        "include_baseline_error": true,
        "n": 340,
        "outlier_excluded": [],
        "reviewed": true,
        "user_excluded": [],
        "value": 53.08738227423457
    }
}