{
    "Ar36": {
        "error": 0.0005981975013109391,
        "error_type": "SEM",
        "filter_outliers_dict": {
            "filter_outliers": true,
            "iterations": 1,
            "std_devs": 3,
            "use_iqr_filtering": false,
            "use_standard_deviation_filtering": false
        },
        "fit": "linear",
        "fn": 340,
        "include_baseline_error": true,
        "n": 340,
        "outlier_excluded": [],
        "reviewed": true,
        "user_excluded": [],
        "value": 0.16107793029575887
    },
    "Ar37": {
        "error": 0.016396239974053047,
        "error_type": "SEM",
        "filter_outliers_dict": {
            "filter_outliers": true,
            "iterations": 1,
            "std_devs": 3,
            "use_iqr_filtering": false,
            "use_standard_deviation_filtering": false
        },
        "fit": "linear",
        "fn": 338,
        "include_baseline_error": true,
        "n": 340,
        "outlier_excluded": [
            322,
            30
        ],
        "reviewed": true,
        "user_excluded": [],
        "value": 4.653360081316161
    },
    "Ar38": {
        "error": 0.0054473931401075185,
        "error_type": "SEM",
        "filter_outliers_dict": {
            "filter_outliers": true,
            "iterations": 1,
            "std_devs": 3,
            "use_iqr_filtering": false,
            "use_standard_deviation_filtering": false
        },
        "fit": "linear",
        "fn": 338,
        "include_baseline_error": true,
        "n": 340,
        "outlier_excluded": [
            306,
            119
        ],
        "reviewed": true,
        "user_excluded": [],
        "value": 0.13053579391853154
    },
    "Ar39": {
        "error": 0.00812675274870353,
        "error_type": "SEM",
        "filter_outliers_dict": {
            "filter_outliers": true,
            "iterations": 1,
            "std_devs": 3,
            "use_iqr_filtering": false,
            "use_standard_deviation_filtering": false
        },
        "fit": "linear",
        "fn": 340,
        "include_baseline_error": true,
        "n": 340,
        "outlier_excluded": [],
        "reviewed": true,
        "user_excluded": [],
        "value": 1.1016686875668935
    },
    "Ar40": {
        "error": 0.033892840641890194,
        "error_type": "SEM",
        "filter_outliers_dict": {
            "filter_outliers": true,
            "iterations": 1,
            "std_devs": 3,
            "use_iqr_filtering": false,
            "use_standard_deviation_filtering": false
        },
        "fit": "parabolic",
        "fn": 339,
        "include_baseline_error": true,
        "n": 340,
        "outlier_excluded": [
            15
        ],
        "reviewed": true,
        "user_excluded": [],
        "value": 54.39385743336962
    }
}